{
  "seen": {
    "1387dfe40f50e2e3": {
      "availability_status": "available",
      "first_seen": "2026-06-16T07:37:14.605931+00:00",
      "last_check_note": "Inserat wurde in den aktuellen Suchergebnissen gefunden.",
      "last_checked": "2026-06-16T08:26:43.437295+00:00",
      "last_seen_in_search": "2026-06-16T08:26:43.437295+00:00",
      "source": "Immowelt Barsinghausen 3 Zimmer",
      "status_changed_at": "2026-06-16T07:51:46.155360+00:00",
      "title": "1 / 8 Neu B 715 € Kaltmiete Wohnung zur Miete 3 Zimmer · 80 m² · 1. Geschoss · frei ab 01.09.2026 Deisterstraße 2, Lohnd",
      "url": "https://www.immowelt.de/expose/8e294093-346c-44a9-8967-daa3ebb898b7"
    },
    "16561d548ea5a165": {
      "availability_status": "available",
      "first_seen": "2026-06-16T07:37:14.605931+00:00",
      "last_check_note": "Inserat wurde in den aktuellen Suchergebnissen gefunden.",
      "last_checked": "2026-06-16T08:26:43.437295+00:00",
      "last_seen_in_search": "2026-06-16T08:26:43.437295+00:00",
      "source": "Immowelt Barsinghausen 3 Zimmer",
      "status_changed_at": "2026-06-16T07:51:46.155360+00:00",
      "title": "1 / 8 E 910 € Kaltmiete Wohnung zur Miete 3 Zimmer · 117 m² · 1. Geschoss Empelde, Ronnenberg (30952) Empelde: Gepflegte",
      "url": "https://www.immowelt.de/expose/174c54e9-b985-4e04-8479-97a466a5da30"
    },
    "40c7559281958119": {
      "first_seen": "2026-06-16T13:50:26.504416+00:00",
      "source": "Kleinanzeigen Barsinghausen 3 Zimmer",
      "title": "Perfekte Familienwohnung in Barsinghausen Die Heide 71 3 Zimmer Wohnung mit Weitblick",
      "url": "https://www.kleinanzeigen.de/s-anzeige/perfekte-familienwohnung-in-barsinghausen-die-heide-71-3-zimmer-wohnung-mit-weitblick/3344014570-203-2862"
    },
    "47392491b8de4c1a": {
      "first_seen": "2026-06-16T13:50:26.504416+00:00",
      "source": "Kleinanzeigen Barsinghausen 3 Zimmer",
      "title": "Sanierte 3 Zimmer Wohnung mit Loggia Aufzug Traumhaftem Weitblick in Barsingh Egestorf",
      "url": "https://www.kleinanzeigen.de/s-anzeige/sanierte-3-zimmer-wohnung-mit-loggia-aufzug-traumhaftem-weitblick-in-barsingh-egestorf/3402468679-203-2862"
    },
    "4beac5d73d4b572d": {
      "availability_status": "available",
      "first_seen": "2026-06-16T07:37:14.605931+00:00",
      "last_check_note": "Inserat wurde in den aktuellen Suchergebnissen gefunden.",
      "last_checked": "2026-06-16T08:26:43.437295+00:00",
      "last_seen_in_search": "2026-06-16T08:26:43.437295+00:00",
      "source": "Immowelt Barsinghausen 3 Zimmer",
      "status_changed_at": "2026-06-16T07:51:46.155360+00:00",
      "title": "Frau Ritz 1 / 10 Neu E 727 € Kaltmiete Wohnung zur Miete 3 Zimmer · 72 m² · 1. Geschoss · frei ab 15.07.2026 Wasserfurch",
      "url": "https://www.immowelt.de/expose/72a7aefe-51c4-4e23-821c-d80db0a70465"
    },
    "5bf0e56ac407c37b": {
      "availability_status": "available",
      "first_seen": "2026-06-16T07:37:14.605931+00:00",
      "last_check_note": "Inserat wurde in den aktuellen Suchergebnissen gefunden.",
      "last_checked": "2026-06-16T08:26:43.437295+00:00",
      "last_seen_in_search": "2026-06-16T08:26:43.437295+00:00",
      "source": "Immowelt Barsinghausen 3 Zimmer",
      "status_changed_at": "2026-06-16T07:51:46.155360+00:00",
      "title": "1 / 10 E 730 € Kaltmiete Wohnung zur Miete 3 Zimmer · 74,5 m² · 5. Geschoss Egestorf, Barsinghausen / Egestorf am Deiste",
      "url": "https://www.immowelt.de/expose/3a096ce6-6ca9-4a11-9a49-a7420aa6c4b2"
    },
    "6b2a66fa75be9009": {
      "first_seen": "2026-06-16T13:50:26.504416+00:00",
      "source": "Kleinanzeigen Barsinghausen 3 Zimmer",
      "title": "3 5 Zi Nichtraucherwhg mit Gr Balkon Einbaukueche",
      "url": "https://www.kleinanzeigen.de/s-anzeige/3-5-zi-nichtraucherwhg-mit-gr-balkon-einbaukueche/3390551070-203-2862"
    },
    "7f68423a322122f9": {
      "first_seen": "2026-06-16T13:50:26.504416+00:00",
      "source": "Kleinanzeigen Barsinghausen 3 Zimmer",
      "title": "3 Zimmer Wohnung mit Einbaukueche als Erstbezug Nach Kernsanierung",
      "url": "https://www.kleinanzeigen.de/s-anzeige/3-zimmer-wohnung-mit-einbaukueche-als-erstbezug-nach-kernsanierung/3431527146-203-2862"
    },
    "7fe05dffb699b575": {
      "availability_status": "available",
      "first_seen": "2026-06-16T07:37:14.605931+00:00",
      "last_check_note": "Inserat wurde in den aktuellen Suchergebnissen gefunden.",
      "last_checked": "2026-06-16T08:26:43.437295+00:00",
      "last_seen_in_search": "2026-06-16T08:26:43.437295+00:00",
      "source": "Immowelt Barsinghausen 3 Zimmer",
      "status_changed_at": "2026-06-16T07:51:46.155360+00:00",
      "title": "von privat 1 / 4 Neu 550 € Kaltmiete Wohnung zur Miete 3 Zimmer · 76 m² · Geschoss 6/7 · frei ab 01.08.2026 Egestorf, Ba",
      "url": "https://www.immowelt.de/expose/26xntsmfhqba"
    },
    "836726824ec5c8aa": {
      "availability_status": "available",
      "first_seen": "2026-06-16T07:18:23.368301+00:00",
      "last_check_note": "Inserat wurde in den aktuellen Suchergebnissen gefunden.",
      "last_checked": "2026-06-16T08:26:43.437295+00:00",
      "last_seen_in_search": "2026-06-16T08:26:43.437295+00:00",
      "source": "Immowelt Barsinghausen 3 Zimmer",
      "status_changed_at": "2026-06-16T07:51:46.155360+00:00",
      "title": "1 / 26 Neu 959 € Kaltmiete Wohnung zur Miete 3 Zimmer · 100,3 m² · EG · frei ab 01.08.2026 Weetzener Straße 12, Sorsum,",
      "url": "https://www.immowelt.de/expose/523021a0-bc7a-46cb-9716-6377cbcaf7fb"
    },
    "8d514956367b35eb": {
      "availability_status": "available",
      "first_seen": "2026-06-16T07:37:14.605931+00:00",
      "last_check_note": "Inserat wurde in den aktuellen Suchergebnissen gefunden.",
      "last_checked": "2026-06-16T08:26:43.437295+00:00",
      "last_seen_in_search": "2026-06-16T08:26:43.437295+00:00",
      "source": "Immowelt Barsinghausen 3 Zimmer",
      "status_changed_at": "2026-06-16T07:51:46.155360+00:00",
      "title": "1 / 4 C 560 € Kaltmiete Wohnung zur Miete 3 Zimmer · 71,8 m² · 1. Geschoss · frei ab 16.07.2026 Freiherr-vom-Stein-Str.",
      "url": "https://www.immowelt.de/expose/293d565b-8197-462b-8305-4f501ae97056"
    },
    "951a576440a61792": {
      "availability_status": "available",
      "first_seen": "2026-06-16T07:37:14.605931+00:00",
      "last_check_note": "Inserat wurde in den aktuellen Suchergebnissen gefunden.",
      "last_checked": "2026-06-16T08:26:43.437295+00:00",
      "last_seen_in_search": "2026-06-16T08:26:43.437295+00:00",
      "source": "Immowelt Barsinghausen 3 Zimmer",
      "status_changed_at": "2026-06-16T07:51:46.155360+00:00",
      "title": "1 / 21 F 684 € Kaltmiete Wohnung zur Miete 3 Zimmer · 72 m² · 1. Geschoss Barsinghausen (30890) Die Wohnung liegt im 1.",
      "url": "https://www.immowelt.de/expose/a69d801b-7125-4757-96e1-9ff804002062"
    },
    "bd6f99e0c74fd8a7": {
      "first_seen": "2026-06-16T13:50:26.504416+00:00",
      "source": "Kleinanzeigen Barsinghausen 3 Zimmer",
      "title": "4 Zimmer Wohnung 3 Etage 92 Qm Fahrstuhl Balkon",
      "url": "https://www.kleinanzeigen.de/s-anzeige/4-zimmer-wohnung-3-etage-92-qm-fahrstuhl-balkon/3435555096-203-2862"
    },
    "bd780341c0d19730": {
      "availability_status": "available",
      "first_seen": "2026-06-16T07:37:14.605931+00:00",
      "last_check_note": "Inserat wurde in den aktuellen Suchergebnissen gefunden.",
      "last_checked": "2026-06-16T08:26:43.437295+00:00",
      "last_seen_in_search": "2026-06-16T08:26:43.437295+00:00",
      "source": "Immowelt Region Hannover 3 Zimmer",
      "status_changed_at": "2026-06-16T07:51:46.155360+00:00",
      "title": "von privat 1 / 7 Neu C 700 € Kaltmiete Wohnung zur Miete 3 Zimmer · 78 m² · Geschoss 3/3 · frei ab 01.07.2026 Ellernstra",
      "url": "https://www.immowelt.de/expose/26yymgwzmldu"
    },
    "c3a053cc5a62a8b0": {
      "first_seen": "2026-06-16T13:50:26.504416+00:00",
      "source": "Kleinanzeigen Barsinghausen 3 Zimmer",
      "title": "Lichtdurchflutete 3 Zimmer Wohnung mit Balkon und Garage",
      "url": "https://www.kleinanzeigen.de/s-anzeige/lichtdurchflutete-3-zimmer-wohnung-mit-balkon-und-garage/3428000964-203-2862"
    },
    "ddc872ce04381a24": {
      "first_seen": "2026-06-16T13:50:26.504416+00:00",
      "source": "Kleinanzeigen Barsinghausen 3 Zimmer",
      "title": "Attraktive 3 Zimmer Wohnung mit Weitblick in Zentraler Lage von Barsinghausen",
      "url": "https://www.kleinanzeigen.de/s-anzeige/attraktive-3-zimmer-wohnung-mit-weitblick-in-zentraler-lage-von-barsinghausen/3419834797-203-2862"
    },
    "e4ad55637515d10e": {
      "availability_status": "available",
      "first_seen": "2026-06-16T07:37:14.605931+00:00",
      "last_check_note": "Inserat wurde in den aktuellen Suchergebnissen gefunden.",
      "last_checked": "2026-06-16T08:26:43.437295+00:00",
      "last_seen_in_search": "2026-06-16T08:26:43.437295+00:00",
      "source": "Immowelt Barsinghausen 3 Zimmer",
      "status_changed_at": "2026-06-16T07:51:46.155360+00:00",
      "title": "1 / 9 Neu C 635 € Kaltmiete Wohnung zur Miete 3 Zimmer · 75 m² · 1. Geschoss · frei ab 01.07.2026 Kirchwehrener Ring 18,",
      "url": "https://www.immowelt.de/expose/a08ad840-bc16-4801-aa81-50ecba610cf1"
    }
  },
  "version": 1
}
